pyionic/__init__.py
pyionic/core.py
pyionic/helpers.py
pyionic/reporting.py
pyionic-0.0.9.dist-info/DESCRIPTION.rst
pyionic-0.0.9.dist-info/LICENSE.txt
pyionic-0.0.9.dist-info/METADATA
pyionic-0.0.9.dist-info/RECORD
pyionic-0.0.9.dist-info/WHEEL
pyionic-0.0.9.dist-info/metadata.json
pyionic-0.0.9.dist-info/top_level.txt
