Metadata-Version: 2.0
Name: pyionic
Version: 0.0.9
Summary: Python package for the Ion Channel API
Home-page: https://github.com/ion-channel/pyionic
Author: Patrick Pierson
Author-email: patrick.pierson@ionchannel.io
License: Apache 2.0
Platform: UNKNOWN
Requires-Python: >=2.7, !=3.0.*, !=3.1.*, !=3.2.*, !=3.3.*
Requires-Dist: requests (>=2.18.4)
